gumo/__init__.py
gumo/logging/__init__.py
gumo_logging-0.0.2.dist-info/LICENSE
gumo_logging-0.0.2.dist-info/METADATA
gumo_logging-0.0.2.dist-info/WHEEL
gumo_logging-0.0.2.dist-info/top_level.txt
gumo_logging-0.0.2.dist-info/RECORD
