Metadata-Version: 2.1
Name: gumo-logging
Version: 0.0.2
Summary: Gumo Logging Library
Home-page: https://github.com/gumo-py/gumo-logging
Author: Gumo Project Team
Author-email: gumo-py@googlegroups.com
License: UNKNOWN
Platform: UNKNOWN
Classifier: Programming Language :: Python :: 3
Classifier: License :: OSI Approved :: MIT License
Classifier: Operating System :: OS Independent
